schedio/__cli__.py
schedio/__init__.py
schedio/_version.py
schedio/conf/__init__.py
schedio/conf/about/__init__.yaml
schedio/conf/batch/__init__.yaml
schedio/conf/cmd/__init__.yaml
schedio/conf/cmd/about.yaml
schedio/conf/cmd/copy_conf.yaml
schedio/conf/cmd/run_task.yaml
schedio/conf/cmd/run_workflow.yaml
schedio/conf/config.yaml
schedio/conf/copier/conf.yaml
schedio/conf/dotenv/__init__.yaml
schedio/conf/hconf.yaml
schedio/conf/hydra/help/help.yaml
schedio/conf/hydra/job_logging/custom.yaml
schedio/conf/joblib/__init__.yaml
schedio/conf/mode/__debug__.yaml
schedio/conf/mode/__init__.yaml
schedio/conf/mode/debug.yaml
schedio/conf/module/__init__.yaml
schedio/conf/path/__batch__.yaml
schedio/conf/path/__default__.yaml
schedio/conf/path/__init__.yaml
schedio/conf/path/__task__.yaml
schedio/conf/pipe/__dataframe__.yaml
schedio/conf/pipe/__dataframe_external_funcs__.yaml
schedio/conf/pipe/__dataframe_instance_methods__.yaml
schedio/conf/pipe/__init__.yaml
schedio/conf/pipe/load_dataframes.yaml
schedio/conf/pipe/save_dataframes.yaml
schedio/conf/pipe/test_preprocessing.yaml
schedio/conf/pipeline/__init__.yaml
schedio/conf/pipeline/__test__.yaml
schedio/conf/project/__init__.yaml
schedio/conf/project/__test__.yaml
schedio/conf/running/__init__.yaml
schedio/conf/task/__batch__.yaml
schedio/conf/task/__init__.yaml
schedio/conf/task/__test__.yaml
schedio/conf/workflow/__init__.yaml
schedio/conf/workflow/__test__.yaml
schedio/project.toml
schedio/py.typed
rompot_schedio-0.1.2.dist-info/LICENSE
rompot_schedio-0.1.2.dist-info/METADATA
rompot_schedio-0.1.2.dist-info/WHEEL
rompot_schedio-0.1.2.dist-info/entry_points.txt
rompot_schedio-0.1.2.dist-info/RECORD
