Metadata-Version: 2.1
Name: rompot-schedio
Version: 0.1.2
Summary: A Python Library for Robotic Drawings
Home-page: https://rompot-schedio.entelecheia.ai
License: MIT
Author: Young Joon Lee
Author-email: entelecheia@hotmail.com
Requires-Python: >=3.8.1,<3.12
Classifier: License :: OSI Approved :: MIT License
Classifier: Programming Language :: Python :: 3
Classifier: Programming Language :: Python :: 3.9
Classifier: Programming Language :: Python :: 3.10
Classifier: Programming Language :: Python :: 3.11
Requires-Dist: click (>=8.1.3,<9.0.0)
Requires-Dist: hyfi (>=0.15.0,<0.16.0)
Project-URL: Repository, https://github.com/entelecheia/rompot-schedio
